{
    "homepage": "https://github.com/epi052/feroxbuster",
    "description": "A fast, simple, recursive content discovery tool written in Rust",
    "version": "2.3.2",
    "license": "MIT",
    "architecture": {
        "64bit": {
            "url": "https://github.com/epi052/feroxbuster/releases/download/v2.3.2/x86_64-windows-feroxbuster.exe.zip",
            "hash": "d9b3822375d7bfd481f42d060c95ce4084da675f31b2c99000e5ed161ec77d60"
        },
        "32bit": {
            "url": "https://github.com/epi052/feroxbuster/releases/download/v2.3.2/x86-windows-feroxbuster.exe.zip",
            "hash": "5edca72a0bbe4d6e41ba76c93cf8b5c50387346fbcd3c7f0c56289d78c68f894"
        }
    },
    "bin": "feroxbuster.exe",
    "checkver": "github",
    "autoupdate": {
        "architecture": {
            "64bit": {
                "url": "https://github.com/epi052/feroxbuster/releases/download/v$version/x86_64-windows-feroxbuster.exe.zip"
            },
            "32bit": {
                "url": "https://github.com/epi052/feroxbuster/releases/download/v$version/x86-windows-feroxbuster.exe.zip"
            }
        }
    }
}
