{
    "version": "2.95",
    "description": "Ethash, ProgPoW, Equihash, CuckooCycle GPU Miner.",
    "homepage": "https://github.com/develsoftware/GMinerRelease",
    "license": "Public Domain",
    "architecture": {
        "64bit": {
            "url": "https://github.com/develsoftware/GMinerRelease/releases/download/2.95/gminer_2_95_windows64.zip",
            "hash": "ac88cad4b9c17450507a216dbb22ee61a413603681e51e78de6ccaa091353acf"
        }
    },
    "bin": [
        [
            "miner.exe",
            "gminer"
        ]
    ],
    "checkver": "github",
    "autoupdate": {
        "architecture": {
            "64bit": {
                "url": "https://github.com/develsoftware/GMinerRelease/releases/download/$version/gminer_$underscoreVersion_windows64.zip"
            }
        }
    }
}
